user_local/__init__.py
user_local/constants.py
user_local/user_local.py
user_local-0.0.22.dist-info/METADATA
user_local-0.0.22.dist-info/WHEEL
user_local-0.0.22.dist-info/top_level.txt
user_local-0.0.22.dist-info/RECORD
